EosQianbaoShizhanKaifa/README.md
EosQianbaoShizhanKaifa/__init__.py
EosQianbaoShizhanKaifa/__main__.py
EosQianbaoShizhanKaifa/file.epub
EosQianbaoShizhanKaifa/index.html
EosQianbaoShizhanKaifa/css/__init__.py
EosQianbaoShizhanKaifa/css/annotations.css
EosQianbaoShizhanKaifa/css/main.css
EosQianbaoShizhanKaifa/css/normalize.css
EosQianbaoShizhanKaifa/css/popup.css
EosQianbaoShizhanKaifa/font/__init__.py
EosQianbaoShizhanKaifa/font/fontello.eot
EosQianbaoShizhanKaifa/font/fontello.svg
EosQianbaoShizhanKaifa/font/fontello.ttf
EosQianbaoShizhanKaifa/font/fontello.woff
EosQianbaoShizhanKaifa/img/__init__.py
EosQianbaoShizhanKaifa/img/annotator-glyph-sprite.png
EosQianbaoShizhanKaifa/img/annotator-icon-sprite.png
EosQianbaoShizhanKaifa/img/apple-touch-icon.png
EosQianbaoShizhanKaifa/img/cancelfullscreen.png
EosQianbaoShizhanKaifa/img/close.png
EosQianbaoShizhanKaifa/img/fullscreen.png
EosQianbaoShizhanKaifa/img/loader.gif
EosQianbaoShizhanKaifa/img/menu-icon.png
EosQianbaoShizhanKaifa/img/save.png
EosQianbaoShizhanKaifa/img/saved.png
EosQianbaoShizhanKaifa/img/settings-s.png
EosQianbaoShizhanKaifa/img/settings.png
EosQianbaoShizhanKaifa/img/star.png
EosQianbaoShizhanKaifa/js/__init__.py
EosQianbaoShizhanKaifa/js/epub.js
EosQianbaoShizhanKaifa/js/epub.min.js
EosQianbaoShizhanKaifa/js/epub.min.map
EosQianbaoShizhanKaifa/js/hooks.min.js
EosQianbaoShizhanKaifa/js/hooks.min.map
EosQianbaoShizhanKaifa/js/reader.js
EosQianbaoShizhanKaifa/js/reader.js.map
EosQianbaoShizhanKaifa/js/reader.min.js
EosQianbaoShizhanKaifa/js/reader.min.map
EosQianbaoShizhanKaifa/js/hooks/__init__.py
EosQianbaoShizhanKaifa/js/hooks/extensions/__init__.py
EosQianbaoShizhanKaifa/js/hooks/extensions/highlight.js
EosQianbaoShizhanKaifa/js/libs/__init__.py
EosQianbaoShizhanKaifa/js/libs/jquery.min.js
EosQianbaoShizhanKaifa/js/libs/localforage.min.js
EosQianbaoShizhanKaifa/js/libs/screenfull.js
EosQianbaoShizhanKaifa/js/libs/screenfull.min.js
EosQianbaoShizhanKaifa/js/libs/zip.min.js
eos_qianbao_shizhan_kaifa-2024.3.5.0.dist-info/METADATA
eos_qianbao_shizhan_kaifa-2024.3.5.0.dist-info/WHEEL
eos_qianbao_shizhan_kaifa-2024.3.5.0.dist-info/entry_points.txt
eos_qianbao_shizhan_kaifa-2024.3.5.0.dist-info/top_level.txt
eos_qianbao_shizhan_kaifa-2024.3.5.0.dist-info/RECORD
